doiowa/__init__.py
doiowa/__main__.py
doiowa/crossref.py
doiowa/md.py
doiowa-2021.8.25.post1.dist-info/METADATA
doiowa-2021.8.25.post1.dist-info/WHEEL
doiowa-2021.8.25.post1.dist-info/entry_points.txt
doiowa-2021.8.25.post1.dist-info/top_level.txt
doiowa-2021.8.25.post1.dist-info/RECORD
