Metadata-Version: 2.1
Name: doiowa
Version: 2021.8.25-1
Summary: UNKNOWN
Home-page: UNKNOWN
License: UNKNOWN
Platform: UNKNOWN
Requires-Dist: crossrefapi
Requires-Dist: lxml
Requires-Dist: requests
